{
    "cabal-extras": {
        "branch": "master",
        "description": "A tool suite to aid Haskell development using `cabal-install`",
        "homepage": null,
        "owner": "phadej",
        "repo": "cabal-extras",
        "rev": "6b94e6044029566f5fee281ca5893c21db5fcae9",
        "sha256": "1lv4flbkbhawxzblm1hf41kyvlh3m7zymwvp1b229nj1fkx7yc1s",
        "type": "tarball",
        "url": "https://github.com/phadej/cabal-extras/archive/6b94e6044029566f5fee281ca5893c21db5fcae9.tar.gz",
        "url_template": "https://github.com/<owner>/<repo>/archive/<rev>.tar.gz"
    },
    "haskell-language-server": {
        "branch": "master",
        "description": "Official haskell ide support via language server (LSP). Successor of ghcide & haskell-ide-engine.",
        "homepage": "",
        "owner": "haskell",
        "repo": "haskell-language-server",
        "rev": "8804cbdf650e85ebb44adf39848d61454c26e8f5",
        "sha256": "1dpyi7civczh1smqaq0g4w7i37cqa3vd8y6nk4g0hrxhslfwi6g7",
        "type": "tarball",
        "url": "https://github.com/haskell/haskell-language-server/archive/8804cbdf650e85ebb44adf39848d61454c26e8f5.tar.gz",
        "url_template": "https://github.com/<owner>/<repo>/archive/<rev>.tar.gz"
    },
    "haskell-nix": {
        "branch": "master",
        "description": "Alternative Haskell Infrastructure for Nixpkgs",
        "homepage": "https://input-output-hk.github.io/haskell.nix",
        "owner": "TerrorJack",
        "repo": "haskell.nix",
        "rev": "5f1857bda3f7e8f7b4e42bcffffb50e83efd90e0",
        "sha256": "13299nwdfpvhfca0akz4ccdkc9rkpjyzmmblmx5nr9qpxfbjbvlx",
        "type": "tarball",
        "url": "https://github.com/TerrorJack/haskell.nix/archive/5f1857bda3f7e8f7b4e42bcffffb50e83efd90e0.tar.gz",
        "url_template": "https://github.com/<owner>/<repo>/archive/<rev>.tar.gz"
    }
}
